{
  "id": "85226611-d150-40ce-82ae-d3086eeef957",
  "project_id": "20bcd0d5-677f-4470-828c-233cfc51e146",
  "feature_id": "49b783bf-7ad7-41fa-91f1-e726821b6a67",
  "type": "stories",
  "name": "",
  "content": "# Transaction Sharing Story\n## Description\nAs a personal finance app user, I want to share my transactions with other users, so that I can manage my finances collaboratively with others.\n\n## Acceptance Criteria\n\n### AC1: Share Single Transaction\n- **Given** I am logged in and have at least one transaction\n- **When** I select a transaction to share and enter the recipient's username or email\n- **Then** The system shares the selected transaction with the recipient\n- **And** The recipient receives a notification about the shared transaction\n\n### AC2: Share Multiple Transactions\n- **Given** I am logged in and have multiple transactions\n- **When** I select multiple transactions to share and enter the recipient's username or email\n- **Then** The system shares all selected transactions with the recipient\n- **And** The recipient receives a notification about the shared transactions\n\n### AC3: Access Control for Shared Transactions\n- **Given** I have shared transactions with another user\n- **When** The recipient attempts to access the shared transactions\n- **Then** The system grants access to the shared transactions based on the permissions set by me\n- **And** The recipient can view the shared transactions according to their permissions\n\n### AC4: Error Handling for Invalid Recipient\n- **Given** I attempt to share a transaction with an invalid recipient\n- **When** The system checks the recipient's username or email\n- **Then** The system displays an error message indicating that the recipient is invalid\n- **And** The transaction is not shared\n\n### AC5: Edge Case - Sharing with Multiple Recipients\n- **Given** I want to share a transaction with multiple recipients\n- **When** I select the transaction and enter the recipients' usernames or emails\n- **Then** The system shares the transaction with all selected recipients\n- **And** Each recipient receives a notification about the shared transaction\n\n## Relevant docs\nFeature spec: [Link to feature specification]\n\n---\n\n# Multi-Account Sharing Story\n## Description\nAs a personal finance app user, I want to share multiple accounts with different permissions, so that I can manage my finances collaboratively with others while controlling access to my accounts.\n\n## Acceptance Criteria\n\n### AC1: Share Multiple Accounts with Read-Only Permission\n- **Given** I am logged in and have multiple accounts\n- **When** I select multiple accounts to share with read-only permission and enter the recipient's username or email\n- **Then** The system shares all selected accounts with the recipient with read-only permission\n- **And** The recipient can view the shared accounts but cannot make changes\n\n### AC2: Share Multiple Accounts with Read-Write Permission\n- **Given** I am logged in and have multiple accounts\n- **When** I select multiple accounts to share with read-write permission and enter the recipient's username or email\n- **Then** The system shares all selected accounts with the recipient with read-write permission\n- **And** The recipient can view and make changes to the shared accounts\n\n### AC3: Access Control for Shared Accounts\n- **Given** I have shared accounts with another user\n- **When** The recipient attempts to access the shared accounts\n- **Then** The system grants access to the shared accounts based on the permissions set by me\n- **And** The recipient can view or make changes to the shared accounts according to their permissions\n\n### AC4: Error Handling for Invalid Account Selection\n- **Given** I attempt to share an invalid account\n- **When** The system checks the account selection\n- **Then** The system displays an error message indicating that the account selection is invalid\n- **And** The account is not shared\n\n### AC5: Edge Case - Sharing Accounts with Different Permissions\n- **Given** I want to share multiple accounts with different recipients and permissions\n- **When** I select the accounts, recipients, and permissions\n- **Then** The system shares the accounts with the recipients according to the set permissions\n- **And** Each recipient can access the shared accounts according to their granted permissions\n\n## Relevant docs\nFeature spec: [Link to feature specification]\n\n---\n\n# Access Control Story\n## Description\nAs a personal finance app user, I want the system to control access to my shared transactions and accounts, so that I can ensure that only authorized users can view or make changes to my financial data.\n\n## Acceptance Criteria\n\n### AC1: Access Control for Shared Transactions\n- **Given** I have shared transactions with another user\n- **When** The recipient attempts to access the shared transactions\n- **Then** The system grants access to the shared transactions based on the permissions set by me\n- **And** The recipient can view the shared transactions according to their permissions\n\n### AC2: Access Control for Shared Accounts\n- **Given** I have shared accounts with another user\n- **When** The recipient attempts to access the shared accounts\n- **Then** The system grants access to the shared accounts based on the permissions set by me\n- **And** The recipient can view or make changes to the shared accounts according to their permissions\n\n### AC3: Unauthorized Access Attempt\n- **Given** An unauthorized user attempts to access my shared transactions or accounts\n- **When** The system checks the user's access level\n- **Then** The system denies access to the shared transactions or accounts\n- **And** The unauthorized user receives an error message indicating that they do not have permission to access the requested data\n\n### AC4: Permission Update\n- **Given** I want to update the permissions for a shared transaction or account\n- **When** I select the shared transaction or account and update the permissions\n- **Then** The system updates the permissions for the shared transaction or account\n- **And** The recipient's access to the shared transaction or account is adjusted according to the updated permissions\n\n## Relevant docs\nFeature spec: [Link to feature specification]\n\n---\n\n# Error Handling Story\n## Description\nAs a personal finance app user, I want the system to handle errors when sharing transactions or accounts, so that I can understand and recover from any issues that occur during the sharing process.\n\n## Acceptance Criteria\n\n### AC1: Error Handling for Invalid Recipient\n- **Given** I attempt to share a transaction or account with an invalid recipient\n- **When** The system checks the recipient's username or email\n- **Then** The system displays an error message indicating that the recipient is invalid\n- **And** The transaction or account is not shared\n\n### AC2: Error Handling for Invalid Account Selection\n- **Given** I attempt to share an invalid account\n- **When** The system checks the account selection\n- **Then** The system displays an error message indicating that the account selection is invalid\n- **And** The account is not shared\n\n### AC3: Error Handling for Permission Issues\n- **Given** I attempt to share a transaction or account with insufficient permissions\n- **When** The system checks my access level\n- **Then** The system displays an error message indicating that I do not have permission to share the transaction or account\n- **And** The transaction or account is not shared\n\n### AC4: Error Handling for System Errors\n- **Given** A system error occurs during the sharing process\n- **When** The system detects the error\n- **Then** The system displays an error message indicating that an error occurred\n- **And** The system logs the error for further investigation\n\n## Relevant docs\nFeature spec: [Link to feature specification]\n\n---\n\n# User Notification Story\n## Description\nAs a personal finance app user, I want to receive notifications when someone shares transactions or accounts with me, so that I can stay informed about changes to my financial data.\n\n## Acceptance Criteria\n\n### AC1: Notification for Shared Transactions\n- **Given** Someone shares a transaction with me\n- **When** The system sends a notification to me\n- **Then** I receive a notification indicating that a transaction has been shared with me\n- **And** I can view the shared transaction from the notification\n\n### AC2: Notification for Shared Accounts\n- **Given** Someone shares an account with me\n- **When** The system sends a notification to me\n- **Then** I receive a notification indicating that an account has been shared with me\n- **And** I can view the shared account from the notification\n\n### AC3: Customizable Notification Settings\n- **Given** I want to customize my notification settings\n- **When** I access the notification settings\n- **Then** I can select which types of notifications I want to receive\n- **And** The system updates my notification settings accordingly\n\n## Relevant docs\nFeature spec: [Link to feature specification]",
  "updated_at": 1772719123740
}